graphdna/__init__.py
graphdna/__main__.py
graphdna/cli.py
graphdna/detectors/__init__.py
graphdna/detectors/checkers.py
graphdna/dna.py
graphdna/entities/__init__.py
graphdna/entities/engines.py
graphdna/entities/interfaces/__init__.py
graphdna/entities/interfaces/dna.py
graphdna/entities/interfaces/heuristics.py
graphdna/heuristics/__init__.py
graphdna/heuristics/gql_queries/__init__.py
graphdna/heuristics/gql_queries/agoo.py
graphdna/heuristics/gql_queries/apollo.py
graphdna/heuristics/gql_queries/ariadne.py
graphdna/heuristics/gql_queries/awsappsync.py
graphdna/heuristics/gql_queries/caliban.py
graphdna/heuristics/gql_queries/dgraph.py
graphdna/heuristics/gql_queries/dianajl.py
graphdna/heuristics/gql_queries/directus.py
graphdna/heuristics/gql_queries/flutter.py
graphdna/heuristics/gql_queries/gqlgen.py
graphdna/heuristics/gql_queries/graphene.py
graphdna/heuristics/gql_queries/graphqlapiforwp.py
graphdna/heuristics/gql_queries/graphqlgo.py
graphdna/heuristics/gql_queries/graphqlgophergo.py
graphdna/heuristics/gql_queries/graphqljava.py
graphdna/heuristics/gql_queries/graphqlphp.py
graphdna/heuristics/gql_queries/graphqlyoga.py
graphdna/heuristics/gql_queries/hasura.py
graphdna/heuristics/gql_queries/hypergraphql.py
graphdna/heuristics/gql_queries/jaal.py
graphdna/heuristics/gql_queries/juniper.py
graphdna/heuristics/gql_queries/lacinia.py
graphdna/heuristics/gql_queries/lighthouse.py
graphdna/heuristics/gql_queries/mercurius.py
graphdna/heuristics/gql_queries/morpheusgraphql.py
graphdna/heuristics/gql_queries/ruby.py
graphdna/heuristics/gql_queries/sangria.py
graphdna/heuristics/gql_queries/stepzen.py
graphdna/heuristics/gql_queries/strawberry.py
graphdna/heuristics/gql_queries/tartiflette.py
graphdna/heuristics/gql_queries/wpgraphql.py
graphdna/heuristics/manager.py
graphdna/heuristics/utils.py
graphdna/heuristics/web_properties/__init__.py
graphdna/heuristics/web_properties/shopify.py
graphdna/http.py
graphdna/logger.py
graphdna/py.typed
graphdna-1.2.2.dist-info/LICENSE
graphdna-1.2.2.dist-info/entry_points.txt
graphdna-1.2.2.dist-info/METADATA
graphdna-1.2.2.dist-info/WHEEL
graphdna-1.2.2.dist-info/RECORD
