Metadata-Version: 2.1
Name: graphdna
Version: 1.2.2
Summary: Fast and powerful GraphQL engine fingerprinting tool
Home-page: https://escape.tech/
License: MIT
Author: Escape Technologies SAS
Author-email: ping@escape.tech
Maintainer: Swan
Maintainer-email: swan@escape.tech
Requires-Python: >=3.7,<4.0
Classifier: License :: OSI Approved :: MIT License
Classifier: Programming Language :: Python :: 3
Classifier: Programming Language :: Python :: 3.7
Classifier: Programming Language :: Python :: 3.8
Classifier: Programming Language :: Python :: 3.9
Classifier: Programming Language :: Python :: 3.10
Classifier: Programming Language :: Python :: 3.11
Requires-Dist: JSON-log-formatter (>=0.5.1,<0.6.0)
Requires-Dist: aiohttp[speedups] (>=3.8.1,<4.0.0)
Project-URL: Bug Tracker, https://github.com/Escape-Technologies/GraphDNA/issues
Project-URL: Repository, https://github.com/Escape-Technologies/GraphDNA
